build/lib/build/lib/build/lib/build/lib/build/lib/build/lib/build/lib/nginx_ldap_auth/__init__.py
build/lib/build/lib/build/lib/build/lib/build/lib/build/lib/build/lib/nginx_ldap_auth/ldap.py
build/lib/build/lib/build/lib/build/lib/build/lib/build/lib/build/lib/nginx_ldap_auth/logging.py
build/lib/build/lib/build/lib/build/lib/build/lib/build/lib/build/lib/nginx_ldap_auth/main.py
build/lib/build/lib/build/lib/build/lib/build/lib/build/lib/build/lib/nginx_ldap_auth/settings.py
build/lib/build/lib/build/lib/build/lib/build/lib/build/lib/build/lib/nginx_ldap_auth/types.py
build/lib/build/lib/build/lib/build/lib/build/lib/build/lib/build/lib/nginx_ldap_auth/app/__init__.py
build/lib/build/lib/build/lib/build/lib/build/lib/build/lib/build/lib/nginx_ldap_auth/app/forms.py
build/lib/build/lib/build/lib/build/lib/build/lib/build/lib/build/lib/nginx_ldap_auth/app/main.py
build/lib/build/lib/build/lib/build/lib/build/lib/build/lib/build/lib/nginx_ldap_auth/app/middleware.py
build/lib/build/lib/build/lib/build/lib/build/lib/build/lib/build/lib/nginx_ldap_auth/app/models.py
build/lib/build/lib/build/lib/build/lib/build/lib/build/lib/build/lib/nginx_ldap_auth/cli/__init__.py
build/lib/build/lib/build/lib/build/lib/build/lib/build/lib/build/lib/nginx_ldap_auth/cli/cli.py
build/lib/build/lib/build/lib/build/lib/build/lib/build/lib/build/lib/nginx_ldap_auth/cli/server.py
build/lib/build/lib/build/lib/build/lib/build/lib/build/lib/doc/source/conf.py
build/lib/build/lib/build/lib/build/lib/build/lib/build/lib/nginx_ldap_auth/__init__.py
build/lib/build/lib/build/lib/build/lib/build/lib/build/lib/nginx_ldap_auth/ldap.py
build/lib/build/lib/build/lib/build/lib/build/lib/build/lib/nginx_ldap_auth/logging.py
build/lib/build/lib/build/lib/build/lib/build/lib/build/lib/nginx_ldap_auth/main.py
build/lib/build/lib/build/lib/build/lib/build/lib/build/lib/nginx_ldap_auth/py.typed
build/lib/build/lib/build/lib/build/lib/build/lib/build/lib/nginx_ldap_auth/settings.py
nginx_ldap_auth_service-2.1.4.dist-info/LICENSE.txt
nginx_ldap_auth_service-2.1.4.dist-info/METADATA
nginx_ldap_auth_service-2.1.4.dist-info/WHEEL
nginx_ldap_auth_service-2.1.4.dist-info/entry_points.txt
nginx_ldap_auth_service-2.1.4.dist-info/top_level.txt
nginx_ldap_auth_service-2.1.4.dist-info/RECORD
